LICENSE
README.md
setup.py
Acquirers/__init__.py
Acquirers.egg-info/PKG-INFO
Acquirers.egg-info/SOURCES.txt
Acquirers.egg-info/dependency_links.txt
Acquirers.egg-info/requires.txt
Acquirers.egg-info/top_level.txt
Acquirers/Rocketpay/__init__.py
Acquirers/Rocketpay/exceptions.py
Acquirers/Tinkoff/__init__.py
Acquirers/Tinkoff/exceptions.py
Acquirers/Tinkoff/receipt.py
Acquirers/Yandexcheckout/__init__.py