Metadata-Version: 2.1
Name: Acquirers
Version: 0.0.6
Summary: UNKNOWN
Home-page: https://github.com/vanzhiganov/acquirers/
Author: Vyacheslav Anzhiganov
Author-email: vanzhiganov@yandex.com
License: UNKNOWN
Project-URL: Source, https://github.com/vanzhiganov/acquirers/
Project-URL: Tracker, https://github.com/vanzhiganov/acquirers/issues
Platform: UNKNOWN
Classifier: Programming Language :: Python :: 3
Classifier: Operating System :: OS Independent
License-File: LICENSE
